querylist/__init__.py
querylist/dict.py
querylist/fieldlookup.py
querylist/list.py
querylist-0.4.0.dist-info/DESCRIPTION.rst
querylist-0.4.0.dist-info/METADATA
querylist-0.4.0.dist-info/metadata.json
querylist-0.4.0.dist-info/RECORD
querylist-0.4.0.dist-info/top_level.txt
querylist-0.4.0.dist-info/WHEEL
tests/__init__.py
tests/base.py
tests/betterdict_dict_tests.py
tests/betterdict_tests.py
tests/betterdictlookup_tests.py
tests/comparator_tests.py
tests/fieldlookup_tests.py
tests/fixtures.py
tests/querylist_list_tests.py
tests/querylist_tests.py
