Metadata-Version: 2.0
Name: querylist
Version: 0.4.0
Summary: This package provides a QueryList class with django ORM-esque filtering, excluding, and getting for lists. It also provides BetterDict, a dot lookup/assignment capable wrapper for dicts that is 100% backwards compatible.
Home-page: https://github.com/thomasw/querylist
Author: Thomas Welfley
Author-email: thomas.welfley+querylist@gmail.com
License: UNKNOWN
Download-URL: https://github.com/thomasw/querylist/downloads
Platform: UNKNOWN
Classifier: Intended Audience :: Developers
Classifier: License :: OSI Approved :: MIT License
Classifier: Topic :: Software Development :: Libraries
